flux_agents/__init__.py
flux_agents/executor_testing.py
flux_agents/testing.py
flux_agents/agents/__init__.py
flux_agents/agents/agent/__init__.py
flux_agents/agents/agent/enums.py
flux_agents/agents/agent/models.py
flux_agents/agents/agent/utils.py
flux_agents/agents/agent/chat/__init__.py
flux_agents/agents/agent/chat/vector.py
flux_agents/agents/agent/hierarchical/__init__.py
flux_agents/agents/agent/hierarchical/models.py
flux_agents/agents/agent/hierarchical/planning_worker.py
flux_agents/agents/agent/hierarchical/prompts.py
flux_agents/agents/agent/hierarchical/react_worker.py
flux_agents/agents/agent/planning/__init__.py
flux_agents/agents/agent/planning/models.py
flux_agents/agents/agent/react/__init__.py
flux_agents/agents/agent/react/models.py
flux_agents/agents/config/__init__.py
flux_agents/agents/config/models.py
flux_agents/agents/monitor/__init__.py
flux_agents/agents/monitor/agent_logs.py
flux_agents/agents/monitor/logger.py
flux_agents/agents/monitor/wrappers/__init__.py
flux_agents/agents/monitor/wrappers/default.py
flux_agents/agents/monitor/wrappers/langfuse.py
flux_agents/agents/monitor/wrappers/logging.py
flux_agents/agents/state/__init__.py
flux_agents/agents/state/models.py
flux_agents/agents/storage/__init__.py
flux_agents/agents/storage/context.py
flux_agents/agents/storage/file.py
flux_agents/agents/storage/filestore.py
flux_agents/agents/storage/message.py
flux_agents/agents/storage/metadata.py
flux_agents/agents/storage/models.py
flux_agents/agents/vectorstore/__init__.py
flux_agents/agents/vectorstore/models.py
flux_agents/agents/vectorstore/truncation.py
flux_agents/agents/vectorstore/default/__init__.py
flux_agents/agents/vectorstore/default/store.py
flux_agents/deployment/__init__.py
flux_agents/deployment/config.py
flux_agents/llm/__init__.py
flux_agents/llm/llm.py
flux_agents/llm/models.py
flux_agents/llm/embeddings/__init__.py
flux_agents/llm/embeddings/batch.py
flux_agents/llm/embeddings/default.py
flux_agents-0.1.6.dist-info/METADATA
flux_agents-0.1.6.dist-info/WHEEL
flux_agents-0.1.6.dist-info/top_level.txt
flux_agents-0.1.6.dist-info/RECORD
