Metadata-Version: 2.2
Name: flux_agents
Version: 0.1.6
Summary: A modern, async-first framework for building AI agents with integrated LLM capabilities and vector operations
Home-page: https://github.com/tiger1def/flux
Author: Christian de Frondeville, Arijit Nukala, Gubi Ganguly
Author-email: christian@flux.ai
Classifier: Development Status :: 3 - Alpha
Classifier: Intended Audience :: Developers
Classifier: License :: OSI Approved :: Apache Software License
Classifier: Operating System :: OS Independent
Classifier: Programming Language :: Python :: 3
Classifier: Programming Language :: Python :: 3.9
Classifier: Programming Language :: Python :: 3.10
Classifier: Programming Language :: Python :: 3.11
Requires-Python: >=3.9
Requires-Dist: msgpack>=1.0.5
Requires-Dist: zstandard
Requires-Dist: pyarrow
Requires-Dist: polars>=0.20.6
Requires-Dist: numpy
Requires-Dist: xmltodict>=0.13.0
Requires-Dist: pyyaml>=6.0.1
Requires-Dist: google-generativeai
Requires-Dist: hnswlib
Requires-Dist: transformers
Requires-Dist: aiofiles
Requires-Dist: aiohttp
Requires-Dist: plotly
Requires-Dist: langfuse
Requires-Dist: diff-match-patch
Requires-Dist: patience
Requires-Dist: pandas
Requires-Dist: tabulate
Provides-Extra: torch
Requires-Dist: torch; extra == "torch"
Requires-Dist: sentence-transformers[torch]>=2.5.0; extra == "torch"
Provides-Extra: dev
Requires-Dist: pytest; extra == "dev"
Requires-Dist: pytest-asyncio; extra == "dev"
Requires-Dist: black; extra == "dev"
Requires-Dist: isort; extra == "dev"
Requires-Dist: mypy; extra == "dev"
Requires-Dist: flake8; extra == "dev"
Provides-Extra: docs
Requires-Dist: sphinx>=7.1.2; extra == "docs"
Requires-Dist: sphinx-rtd-theme>=1.3.0; extra == "docs"
Requires-Dist: myst-parser>=2.0.0; extra == "docs"
Requires-Dist: sphinx-autodoc-typehints>=1.25.2; extra == "docs"
Dynamic: author
Dynamic: author-email
Dynamic: classifier
Dynamic: description
Dynamic: description-content-type
Dynamic: home-page
Dynamic: provides-extra
Dynamic: requires-dist
Dynamic: requires-python
Dynamic: summary
